potatorch/__init__.py
potatorch/callbacks.py
potatorch/training.py
potatorch/utils.py
potatorch/datasets/FilteredDataset.py
potatorch/datasets/__init__.py
potatorch/datasets/utils.py
potatorch/losses/MSRELoss.py
potatorch/losses/WDLLoss.py
potatorch/losses/__init__.py
potatorch/models/__init__.py
potatorch/models/cnn.py
potatorch/optimization/__init__.py
potatorch/optimization/bayesian_optimizer.py
potatorch/optimization/tuning.py
potatorch-0.0.5.dist-info/METADATA
potatorch-0.0.5.dist-info/WHEEL
potatorch-0.0.5.dist-info/licenses/LICENSE
potatorch-0.0.5.dist-info/RECORD
