Metadata-Version: 2.4
Name: potatorch
Version: 0.0.5
Summary: Lightweight high-level PyTorch framework that runs on potato machines
Project-URL: Homepage, https://github.com/crybot/potatorch
Project-URL: Bug Tracker, https://github.com/crybot/potatorch/issues
Author-email: Marco Pampaloni <marco.pampaloni1@gmail.com>
License-File: LICENSE
Keywords: deep learning,framework,limited resources,machine learning,python,pytorch
Classifier: License :: OSI Approved :: MIT License
Classifier: Operating System :: OS Independent
Classifier: Programming Language :: Python :: 3
Requires-Python: >=3.8
